genie/libs/clean/__init__.py
genie/libs/clean/clean.json
genie/libs/clean/clean.py
genie/libs/clean/exception.py
genie/libs/clean/utils.py
genie/libs/clean/cli/__init__.py
genie/libs/clean/cli/commands.py
genie/libs/clean/recovery/__init__.py
genie/libs/clean/recovery/dialogs.py
genie/libs/clean/recovery/recovery.py
genie/libs/clean/recovery/iosxe/__init__.py
genie/libs/clean/recovery/iosxe/dialogs.py
genie/libs/clean/recovery/iosxe/recovery.py
genie/libs/clean/recovery/iosxe/cat3k/__init__.py
genie/libs/clean/recovery/iosxe/cat3k/dialogs.py
genie/libs/clean/recovery/iosxe/sdwan/__init__.py
genie/libs/clean/recovery/iosxe/sdwan/dialogs.py
genie/libs/clean/recovery/iosxe/sdwan/recovery.py
genie/libs/clean/recovery/iosxr/__init__.py
genie/libs/clean/recovery/iosxr/dialogs.py
genie/libs/clean/recovery/iosxr/recovery.py
genie/libs/clean/recovery/nxos/__init__.py
genie/libs/clean/recovery/nxos/dialogs.py
genie/libs/clean/recovery/nxos/recovery.py
genie/libs/clean/recovery/nxos/n3k/__init__.py
genie/libs/clean/recovery/nxos/n3k/recovery.py
genie/libs/clean/recovery/nxos/n7k/__init__.py
genie/libs/clean/recovery/nxos/n7k/recovery.py
genie/libs/clean/recovery/nxos/n9k/__init__.py
genie/libs/clean/recovery/nxos/n9k/recovery.py
genie/libs/clean/stages/__init__.py
genie/libs/clean/stages/image_handler.py
genie/libs/clean/stages/stages.py
genie/libs/clean/stages/aireos/__init__.py
genie/libs/clean/stages/aireos/stages.py
genie/libs/clean/stages/apic/__init__.py
genie/libs/clean/stages/apic/image_handler.py
genie/libs/clean/stages/apic/stages.py
genie/libs/clean/stages/apic/tests/__init__.py
genie/libs/clean/stages/apic/tests/test_apply_configuration.py
genie/libs/clean/stages/apic/tests/test_copy_to_device.py
genie/libs/clean/stages/apic/tests/test_fabric_clean.py
genie/libs/clean/stages/apic/tests/test_image_handler.py
genie/libs/clean/stages/apic/tests/test_node_registration.py
genie/libs/clean/stages/cheetah/__init__.py
genie/libs/clean/stages/cheetah/stages.py
genie.libs.clean-25.9.dist-info/METADATA
genie.libs.clean-25.9.dist-info/WHEEL
genie.libs.clean-25.9.dist-info/entry_points.txt
genie.libs.clean-25.9.dist-info/top_level.txt
genie.libs.clean-25.9.dist-info/RECORD
